MANIFEST.in
setup.py
django_multi_fk.egg-info/PKG-INFO
django_multi_fk.egg-info/SOURCES.txt
django_multi_fk.egg-info/dependency_links.txt
django_multi_fk.egg-info/requires.txt
django_multi_fk.egg-info/top_level.txt
multi_fk/__init__.py
multi_fk/apps.py
multi_fk/static/admin/js/multi_fk.js