Metadata-Version: 1.1
Name: django-multi-fk
Version: 0.1.1
Summary: Automatically update multiple foreign keys in the Django admin
Home-page: https://github.com/nathan-osman/django-multi-fk
Author: Nathan Osman
Author-email: nathan@quickmediasolutions.com
License: MIT
Platform: UNKNOWN
Classifier: Development Status :: 5 - Production/Stable
Classifier: Environment :: Web Environment
Classifier: Framework :: Django
Classifier: Intended Audience :: Developers
Classifier: License :: OSI Approved :: MIT License
Classifier: Operating System :: OS Independent
Classifier: Programming Language :: Python
Classifier: Programming Language :: Python :: 2
Classifier: Programming Language :: Python :: 3
Classifier: Topic :: Software Development :: Libraries :: Python Modules
